cli/lstorage.py
lztools.storage-1.0.11.dist-info/LICENSE.txt
lztools.storage-1.0.11.dist-info/METADATA
lztools.storage-1.0.11.dist-info/RECORD
lztools.storage-1.0.11.dist-info/WHEEL
lztools.storage-1.0.11.dist-info/entry_points.txt
lztools.storage-1.0.11.dist-info/top_level.txt
